httptestserver/__init__.py
httptestserver/http_server.py
httptestserver/testing.py
httptestserver/smtp_server.py
httptestserver/server.pem
httptestserver/_compat.py
httptestserver-0.3.1.dist-info/DESCRIPTION.rst
httptestserver-0.3.1.dist-info/RECORD
httptestserver-0.3.1.dist-info/top_level.txt
httptestserver-0.3.1.dist-info/WHEEL
httptestserver-0.3.1.dist-info/metadata.json
httptestserver-0.3.1.dist-info/METADATA
