Metadata-Version: 2.0
Name: httptestserver
Version: 0.3.1
Summary: HTTP(s) and SMTP testing server
Home-page: UNKNOWN
Author: Javier Santacruz
Author-email: javier.santacruz.lc@gmail.com
License: UNKNOWN
Platform: UNKNOWN
Classifier: Topic :: Software Development :: Testing
